{
    "_links": {
        "self": {
            "href": "http:\/\/default\/manage-policy-comings-soon?_format=hal_json"
        },
        "type": {
            "href": "http:\/\/drupal.org\/rest\/type\/node\/listing_pages"
        },
        "http:\/\/drupal.org\/rest\/relation\/node\/listing_pages\/revision_uid": [
            {
                "href": "http:\/\/default\/user\/1?_format=hal_json"
            }
        ],
        "http:\/\/drupal.org\/rest\/relation\/node\/listing_pages\/uid": [
            {
                "href": "http:\/\/default\/user\/1?_format=hal_json",
                "lang": "en"
            }
        ]
    },
    "nid": [
        {
            "value": 1443
        }
    ],
    "uuid": [
        {
            "value": "7f287c0d-1a3a-4847-8fa5-96b8cf598607"
        }
    ],
    "vid": [
        {
            "value": 3967
        }
    ],
    "langcode": [
        {
            "value": "en",
            "lang": "en"
        }
    ],
    "type": [
        {
            "target_id": "listing_pages"
        }
    ],
    "revision_timestamp": [
        {
            "value": "2021-01-06T14:55:41+00:00",
            "format": "Y-m-d\\TH:i:sP"
        }
    ],
    "_embedded": {
        "http:\/\/drupal.org\/rest\/relation\/node\/listing_pages\/revision_uid": [
            {
                "_links": {
                    "self": {
                        "href": "http:\/\/default\/user\/1?_format=hal_json"
                    },
                    "type": {
                        "href": "http:\/\/drupal.org\/rest\/type\/user\/user"
                    }
                },
                "uuid": [
                    {
                        "value": "1c516dcb-eef0-4d31-bdcd-1dd660d651b9"
                    }
                ]
            }
        ],
        "http:\/\/drupal.org\/rest\/relation\/node\/listing_pages\/uid": [
            {
                "_links": {
                    "self": {
                        "href": "http:\/\/default\/user\/1?_format=hal_json"
                    },
                    "type": {
                        "href": "http:\/\/drupal.org\/rest\/type\/user\/user"
                    }
                },
                "uuid": [
                    {
                        "value": "1c516dcb-eef0-4d31-bdcd-1dd660d651b9"
                    }
                ],
                "lang": "en"
            }
        ]
    },
    "status": [
        {
            "value": true,
            "lang": "en"
        }
    ],
    "title": [
        {
            "value": "Manage Policy Coming Soon",
            "lang": "en"
        }
    ],
    "created": [
        {
            "value": "2021-01-06T10:17:34+00:00",
            "lang": "en",
            "format": "Y-m-d\\TH:i:sP"
        }
    ],
    "changed": [
        {
            "value": "2021-01-06T14:55:41+00:00",
            "lang": "en",
            "format": "Y-m-d\\TH:i:sP"
        }
    ],
    "promote": [
        {
            "value": false,
            "lang": "en"
        }
    ],
    "sticky": [
        {
            "value": false,
            "lang": "en"
        }
    ],
    "default_langcode": [
        {
            "value": true,
            "lang": "en"
        }
    ],
    "metatag": [
        {
            "value": {
                "canonical_url": "http:\/\/default\/manage-policy-comings-soon",
                "title": "Manage Policy Coming Soon | Profiling",
                "description": ""
            }
        }
    ],
    "path": [
        {
            "alias": "\/manage-policy-comings-soon",
            "pid": 37,
            "langcode": "en",
            "lang": "en"
        }
    ],
    "body": [
        {
            "value": "<p><img alt=\"Coming soon\" data-entity-type=\"file\" data-entity-uuid=\"2462b082-8427-4ba7-b3f4-2b4822208277\" src=\"\/sites\/default\/files\/inline-images\/comingsoon_0.png\" \/><\/p>\r\n",
            "format": "basic_html",
            "processed": "<p><img alt=\"Coming soon\" data-entity-type=\"file\" data-entity-uuid=\"2462b082-8427-4ba7-b3f4-2b4822208277\" src=\"\/sites\/default\/files\/inline-images\/comingsoon_0.png\" \/><\/p>",
            "summary": "",
            "lang": "en"
        }
    ],
    "layout_builder__layout": [
        {
            "section": {
                "layout_id": "ds_1col",
                "layout_settings": {
                    "label": "",
                    "wrappers": {
                        "ds_content": "div"
                    },
                    "outer_wrapper": "div",
                    "attributes": "",
                    "link_attribute": "",
                    "link_custom": "",
                    "classes": {
                        "layout_class": []
                    }
                },
                "components": [
                    {
                        "uuid": "3ebb8976-239c-471e-966a-c012522d906b",
                        "region": "ds_content",
                        "configuration": {
                            "id": "field_block:node:listing_pages:body",
                            "label": "Landing page Description",
                            "provider": "layout_builder",
                            "label_display": 0,
                            "formatter": {
                                "label": "hidden",
                                "type": "text_default",
                                "settings": [],
                                "third_party_settings": []
                            },
                            "context_mapping": {
                                "entity": "layout_builder.entity",
                                "view_mode": "view_mode"
                            }
                        },
                        "additional": [],
                        "weight": 0
                    }
                ],
                "third_party_settings": []
            }
        }
    ]
}